MANIFEST.in
VERSION
distribute_setup.py
setup.cfg
setup.py
lib/intessa/__init__.py
lib/intessa/api.py
lib/intessa/http.py
lib/intessa/response.py
lib/intessa.egg-info/PKG-INFO
lib/intessa.egg-info/SOURCES.txt
lib/intessa.egg-info/dependency_links.txt
lib/intessa.egg-info/requires.txt
lib/intessa.egg-info/top_level.txt
lib/intessa/conneg/__init__.py
lib/intessa/conneg/accept.py
lib/intessa/conneg/codec_base.py
lib/intessa/conneg/content_type.py
lib/intessa/conneg/streaming.py
lib/intessa/conneg/default/__init__.py
lib/intessa/conneg/default/forms.py
lib/intessa/conneg/default/json.py
lib/intessa/conneg/default/multipart.py
lib/intessa/conneg/default/text.py
lib/intessa/conneg/default/xml.py
lib/intessa/utils/__init__.py
lib/intessa/utils/caseless_dict.py
lib/intessa/vendor/__init__.py
lib/intessa/vendor/abc.py
lib/intessa/vendor/abcoll.py
lib/intessa/vendor/multidict.py
lib/intessa/vendor/weakrefset.py