Metadata-Version: 1.0
Name: intessa
Version: 2.0.0
Summary: Zero-configuration dynamic interfaces to HTTP APIs.
Home-page: http://github.com/zacharyvoase/intessa
Author: Zachary Voase
Author-email: z@zacharyvoase.com
License: UNKNOWN
Platform: UNKNOWN
